resfo/__init__.py
resfo/array_entry.py
resfo/errors.py
resfo/format.py
resfo/py.typed
resfo/read.py
resfo/types.py
resfo/version.py
resfo/write.py
resfo/_formatted/__init__.py
resfo/_formatted/read.py
resfo/_formatted/write.py
resfo/_unformatted/__init__.py
resfo/_unformatted/common.py
resfo/_unformatted/read.py
resfo/_unformatted/write.py
resfo-5.0.1.dist-info/licenses/LICENSE.md
resfo-5.0.1.dist-info/METADATA
resfo-5.0.1.dist-info/WHEEL
resfo-5.0.1.dist-info/top_level.txt
resfo-5.0.1.dist-info/RECORD
