Metadata-Version: 2.4
Name: resfo
Version: 5.0.1
Summary: A (lazy) parser and writer for reservoir simulator fortran output format.
Author-email: Equinor <fg_sib-scout@equinor.com>
Maintainer-email: Eivind Jahren <ejah@equinor.com>
License-Expression: LGPL-3.0-or-later
Project-URL: Homepage, https://github.com/equinor/resfo
Project-URL: Repository, https://github.com/equinor/resfo
Project-URL: Documentation, https://resfo.readthedocs.io/en/stable/
Project-URL: Bug Tracker, https://github.com/equinor/resfo/issues
Classifier: Development Status :: 6 - Mature
Classifier: Programming Language :: Python
Classifier: Programming Language :: Python :: 3.10
Classifier: Programming Language :: Python :: 3.11
Classifier: Programming Language :: Python :: 3.12
Classifier: Programming Language :: Python :: 3.13
Classifier: Programming Language :: Python :: 3.14
License-File: LICENSE.md
Requires-Dist: numpy
Requires-Dist: typing_extensions
Provides-Extra: doc
Requires-Dist: sphinx; extra == "doc"
Requires-Dist: sphinx-rtd-theme; extra == "doc"
Provides-Extra: dev
Requires-Dist: pytest; extra == "dev"
Requires-Dist: hypothesis; extra == "dev"
Requires-Dist: tox; extra == "dev"
Requires-Dist: pre-commit; extra == "dev"
Dynamic: license-file
